{
  "name": "Webhooks",
  "icon": "pipe.png",
  "itemsOrdered": [
    {
      "name": "Intro",
      "file": "intro.md",
      "subCat": "Intro"
    },
    {
      "name": "What are Webhooks",
      "file": "what-are-webhooks.md",
      "subCat": "Overview"
    },
    {
      "name": "Supported Events & Resources",
      "file": "webhooks-supported-events-resources.md",
      "subCat": "Overview"
    },
    {
      "name": "Setup",
      "file": "webhooks-setup.md",
      "subCat": "Implementation"
    },
    {
      "name": "Testing",
      "file": "webhooks-testing.md",
      "subCat": "Implementation"
    },
    {
      "name": "Data Structures",
      "file": "webhooks-structures.md",
      "subCat": "Implementation"
    },
    {
      "name": "Security & API Tokens",
      "file": "webhooks-api-tokens.md",
      "subCat": "Implementation"
    },
    {
      "name": "How it Works",
      "file": "webhooks-how-it-works.md",
      "subCat": "Behind The Scenes"
    },
    {
      "name": "In Conclusion",
      "file": "conclusion.md",
      "subCat": "Conclusion"
    }
  ]
}
