{
  "name": "Biblioteca de Angular",
  "pageHeader": "Agregar comentarios a tu aplicación Angular",
  "itemsOrdered": [
    {
      "name": "Demostración en vivo",
      "file": "live-demo-readme-generated.md",
      "subCat": "Documentación",
      "type": "readme"
    },
    {
      "name": "Instalación",
      "file": "installation-readme-generated.md",
      "subCat": "Primeros pasos",
      "type": "readme"
    },
    {
      "name": "Estructura del proyecto",
      "file": "project-structure-readme-generated.md",
      "subCat": "Documentación",
      "type": "readme"
    },
    {
      "name": "Estado de mantenimiento",
      "file": "maintenance-status-readme-generated.md",
      "subCat": "Documentación",
      "type": "readme"
    }
  ]
}