{
  "name": "Seitenreaktionen",
  "icon": "heart.svg",
  "itemsOrdered": [
    {
      "name": "Seitenreaktionen",
      "file": "page-reacts-about.md",
      "subCat": "Seitenreaktionen"
    },
    {
      "name": "Installation - VanillaJS",
      "file": "page-reacts-installation-vanillajs.md",
      "subCat": "Seitenreaktionen"
    },
    {
      "name": "Das schwebende Gef채llt mir-Widget",
      "file": "floating-likes-about.md",
      "subCat": "Schwebendes Gef채llt mir-Widget"
    },
    {
      "name": "Installation - VanillaJS",
      "file": "floating-likes-installation-vanillajs.md",
      "subCat": "Schwebendes Gef채llt mir-Widget"
    },
    {
      "name": "Installation - WordPress",
      "file": "floating-likes-wordpress.md",
      "subCat": "Schwebendes Gef채llt mir-Widget"
    }
  ]
}