{
  "name": "React Native SDK",
  "pageHeader": "Додавање коментара у вашу React Native апликацију",
  "itemsOrdered": [
    {
      "name": "Инсталација",
      "file": "installation-readme-generated.md",
      "subCat": "Почетак",
      "type": "readme"
    },
    {
      "name": "О",
      "file": "about-readme-generated.md",
      "subCat": "Документација",
      "type": "readme"
    },
    {
      "name": "Снимци екрана",
      "file": "screenshots-readme-generated.md",
      "subCat": "Документација",
      "type": "readme"
    }
  ]
}