{
  "name": "React Native SDK",
  "pageHeader": "React Native uygulamanıza yorum ekleyin",
  "itemsOrdered": [
    {
      "name": "Canlı Demo",
      "file": "live-demo-readme-generated.md",
      "subCat": "Dokümantasyon",
      "type": "readme"
    },
    {
      "name": "Kurulum",
      "file": "installation-readme-generated.md",
      "subCat": "Başlarken",
      "type": "readme"
    },
    {
      "name": "Hakkında",
      "file": "about-readme-generated.md",
      "subCat": "Dokümantasyon",
      "type": "readme"
    },
    {
      "name": "Ekran Görüntüleri",
      "file": "screenshots-readme-generated.md",
      "subCat": "Dokümantasyon",
      "type": "readme"
    }
  ]
}