{
  "name": "Библиотека для React Native",
  "pageHeader": "Добавьте виджеты комментариев в ваше приложение React Native",
  "itemsOrdered": [
    {
      "name": "Демонстрация в реальном времени",
      "file": "live-showcase-readme-generated.md",
      "subCat": "Документация",
      "type": "readme"
    },
    {
      "name": "Установка",
      "file": "installation-readme-generated.md",
      "subCat": "Начало работы",
      "type": "readme"
    },
    {
      "name": "Рассмотрите возможность использования нативного SDK",
      "file": "consider-the-native-sdk-readme-generated.md",
      "subCat": "Документация",
      "type": "readme"
    },
    {
      "name": "Использование — виджет комментариев в реальном времени",
      "file": "usage-the-live-comment-widget-readme-generated.md",
      "subCat": "Использование",
      "type": "readme"
    },
    {
      "name": "Использование — виджет чата в реальном времени",
      "file": "usage-the-live-chat-widget-readme-generated.md",
      "subCat": "Использование",
      "type": "readme"
    },
    {
      "name": "Использование — SSO",
      "file": "usage-sso-readme-generated.md",
      "subCat": "Использование",
      "type": "readme"
    },
    {
      "name": "Peer-зависимости",
      "file": "peer-dependencies-readme-generated.md",
      "subCat": "Документация",
      "type": "readme"
    },
    {
      "name": "Статус поддержки",
      "file": "maintenance-status-readme-generated.md",
      "subCat": "Документация",
      "type": "readme"
    }
  ]
}