{
  "name": "React Native-bibliotheek",
  "pageHeader": "Voeg commentaarwidgets toe aan je React Native-app",
  "itemsOrdered": [
    {
      "name": "Installatie",
      "file": "installation-readme-generated.md",
      "subCat": "Aan de slag",
      "type": "readme"
    },
    {
      "name": "Overweeg de Native SDK",
      "file": "consider-the-native-sdk-readme-generated.md",
      "subCat": "Documentatie",
      "type": "readme"
    },
    {
      "name": "Gebruik - De live commentaarwidget",
      "file": "usage-the-live-comment-widget-readme-generated.md",
      "subCat": "Gebruik",
      "type": "readme"
    },
    {
      "name": "Gebruik - De live chatwidget",
      "file": "usage-the-live-chat-widget-readme-generated.md",
      "subCat": "Gebruik",
      "type": "readme"
    },
    {
      "name": "Gebruik - SSO",
      "file": "usage-sso-readme-generated.md",
      "subCat": "Gebruik",
      "type": "readme"
    },
    {
      "name": "Peer-afhankelijkheden",
      "file": "peer-dependencies-readme-generated.md",
      "subCat": "Documentatie",
      "type": "readme"
    }
  ]
}