{
  "name": "Instalación de Moodle",
  "pageHeader": "Añadir comentarios a sitios de Moodle",
  "icon": "3rd-party-products/moodle.png",
  "itemsOrdered": [
    {
      "name": "Inicio rápido",
      "file": "moodle-quick-start.md",
      "subCat": "Resumen"
    },
    {
      "name": "Instalación",
      "file": "moodle-installation.md",
      "subCat": "Instalación del complemento de Moodle"
    },
    {
      "name": "Configuración",
      "file": "moodle-configuration.md",
      "subCat": "Instalación del complemento de Moodle"
    },
    {
      "name": "Estilos de comentarios",
      "file": "moodle-commenting-styles.md",
      "subCat": "Instalación del complemento de Moodle"
    },
    {
      "name": "Modos SSO",
      "file": "moodle-sso-modes.md",
      "subCat": "Instalación del complemento de Moodle"
    },
    {
      "name": "Preferencias de notificación del usuario",
      "file": "moodle-user-preferences.md",
      "subCat": "Instalación del complemento de Moodle"
    },
    {
      "name": "Personalización",
      "file": "moodle-customize.md",
      "subCat": "Instalación del complemento de Moodle"
    },
    {
      "name": "Errores de dominio",
      "file": "moodle-domain-errors.md",
      "subCat": "Instalación del complemento de Moodle"
    }
  ]
}