{
  "name": "Instalacija Shopifya",
  "pageHeader": "Dodajte komentare na Shopify stranice",
  "icon": "3rd-party-products/shopify.svg",
  "itemsOrdered": [
    {
      "name": "Instalirajte aplikaciju FastComments",
      "file": "shopify-install.md",
      "subCat": "Instalacija Shopifya"
    },
    {
      "name": "Dodajte komentare na objave bloga i proizvode",
      "file": "shopify-add-comments.md",
      "subCat": "Instalacija Shopifya"
    },
    {
      "name": "Dodajte oznaku s brojem komentara",
      "file": "shopify-comment-count.md",
      "subCat": "Instalacija Shopifya"
    },
    {
      "name": "Dodajte feed najnovijih komentara",
      "file": "shopify-recent-comments.md",
      "subCat": "Instalacija Shopifya"
    },
    {
      "name": "Dodajte feed najnovijih rasprava",
      "file": "shopify-recent-discussions.md",
      "subCat": "Instalacija Shopifya"
    },
    {
      "name": "Dodajte popis najpopularnijih stranica",
      "file": "shopify-top-pages.md",
      "subCat": "Instalacija Shopifya"
    },
    {
      "name": "Dodajte sažetak recenzija",
      "file": "shopify-reviews-summary.md",
      "subCat": "Instalacija Shopifya"
    },
    {
      "name": "Automatsko prijavljivanje Shopify kupaca",
      "file": "shopify-sso.md",
      "subCat": "Instalacija Shopifya"
    },
    {
      "name": "Uvezite postojeće komentare",
      "file": "shopify-import.md",
      "subCat": "Instalacija Shopifya"
    },
    {
      "name": "Prilagodba",
      "file": "shopify-customize.md",
      "subCat": "Instalacija Shopifya"
    },
    {
      "name": "Pogreške domene",
      "file": "shopify-domain-errors.md",
      "subCat": "Instalacija Shopifya"
    },
    {
      "name": "Ručno instaliranje (napredno)",
      "file": "shopify-manual-install.md",
      "subCat": "Instalacija Shopifya"
    }
  ]
}