{
  "name": "ספריית Svelte",
  "pageHeader": "הוספת תגובות לאפליקציית Svelte שלך",
  "itemsOrdered": [
    {
      "name": "הדגמה חיה",
      "file": "live-demo-readme-generated.md",
      "subCat": "תיעוד",
      "type": "readme"
    },
    {
      "name": "התקנה",
      "file": "install-readme-generated.md",
      "subCat": "התחלה מהירה",
      "type": "readme"
    },
    {
      "name": "התחלה מהירה",
      "file": "quick-start-readme-generated.md",
      "subCat": "תיעוד",
      "type": "readme"
    },
    {
      "name": "ווידג'טים",
      "file": "widgets-readme-generated.md",
      "subCat": "תיעוד",
      "type": "readme"
    },
    {
      "name": "פיתוח",
      "file": "developing-readme-generated.md",
      "subCat": "תיעוד",
      "type": "readme"
    },
    {
      "name": "בנייה",
      "file": "building-readme-generated.md",
      "subCat": "תיעוד",
      "type": "readme"
    },
    {
      "name": "מצב תחזוקה",
      "file": "maintenance-status-readme-generated.md",
      "subCat": "תיעוד",
      "type": "readme"
    }
  ]
}