{
  "name": "Installation sur Hostinger",
  "pageHeader": "Ajouter des commentaires en direct aux sites Hostinger",
  "icon": "3rd-party-products/hostinger.png",
  "itemsOrdered": [
    {
      "name": "Étape 1 : Ajouter le widget de code",
      "file": "hostinger-step-1.md",
      "subCat": "Installation du site Hostinger"
    },
    {
      "name": "Étape 2 : Ajouter le code",
      "file": "hostinger-step-2.md",
      "subCat": "Installation du site Hostinger"
    },
    {
      "name": "Succès",
      "file": "hostinger-site-success.md",
      "subCat": "Installation du site Hostinger"
    },
    {
      "name": "Erreurs de domaine du site",
      "file": "hostinger-site-domain-errors.md",
      "subCat": "Installation du site Hostinger"
    },
    {
      "name": "Personnalisation du site",
      "file": "hostinger-site-customize.md",
      "subCat": "Installation du site Hostinger"
    },
    {
      "name": "Bouton flottant « J'aime »",
      "file": "hostinger-floating-likes.md",
      "subCat": "Boutons « J'aime » flottants Hostinger"
    }
  ]
}