{
  "name": "Εγκατάσταση WordPress",
  "pageHeader": "Προσθήκη ζωντανών σχολίων σε ιστότοπους WordPress",
  "icon": "3rd-party-products/wordpress.png",
  "itemsOrdered": [
    {
      "name": "Γρήγορη εκκίνηση",
      "file": "wordpress-quick-start.md",
      "subCat": "Συνοπτικά"
    },
    {
      "name": "Εγκατάσταση",
      "file": "wordpress-installation.md",
      "subCat": "Εγκατάσταση WordPress"
    },
    {
      "name": "Προσαρμογή",
      "file": "wordpress-customize.md",
      "subCat": "Εγκατάσταση WordPress"
    },
    {
      "name": "Διαχείριση σχολίων",
      "file": "wordpress-moderation.md",
      "subCat": "Εγκατάσταση WordPress"
    },
    {
      "name": "Χρήστες, Συντονιστές και Διαχειριστές",
      "file": "wordpress-users-moderators-admins.md",
      "subCat": "Εγκατάσταση WordPress"
    },
    {
      "name": "Ιστότοποι μόνο για μέλη (SSO)",
      "file": "wordpress-membership-sites.md",
      "subCat": "Εγκατάσταση WordPress"
    },
    {
      "name": "Ειδοποιήσεις",
      "file": "wordpress-notifications.md",
      "subCat": "Εγκατάσταση WordPress"
    },
    {
      "name": "Προσαρμοσμένα θέματα",
      "file": "wordpress-custom-themes.md",
      "subCat": "Εγκατάσταση WordPress"
    },
    {
      "name": "Συγχρονισμός προς το WordPress",
      "file": "wordpress-syncing-back-to-wp.md",
      "subCat": "Εγκατάσταση WordPress"
    },
    {
      "name": "Αριθμός σχολίων",
      "file": "wordpress-comment-counts.md",
      "subCat": "Εγκατάσταση WordPress"
    },
    {
      "name": "Επικοινωνία μεταξύ WordPress και διακομιστή FastComment",
      "file": "wordpress-server-communication.md",
      "subCat": "Εγκατάσταση WordPress"
    },
    {
      "name": "Σφάλματα τομέα",
      "file": "wordpress-domain-errors.md",
      "subCat": "Εγκατάσταση WordPress"
    },
    {
      "name": "Widget: Πρόσφατα σχόλια",
      "file": "wordpress-recent-comments-widget.md",
      "subCat": "Άλλα widgets"
    },
    {
      "name": "Widget: Πρόσφατες συζητήσεις",
      "file": "wordpress-recent-discussions-widget.md",
      "subCat": "Άλλα widgets"
    },
    {
      "name": "Widget: Κορυφαίες σελίδες",
      "file": "wordpress-top-pages-widget.md",
      "subCat": "Άλλα widgets"
    },
    {
      "name": "Απενεργοποίηση έναντι απεγκατάστασης του πρόσθετου",
      "file": "wordpress-deactivating-vs-uninstalling.md",
      "subCat": "Κατάργηση πρόσθετου"
    }
  ]
}