{
  "name": "影像聊天",
  "icon": "image-chat-icon.svg",
  "itemsOrdered": [
    {
      "name": "入門指南",
      "file": "getting-started.md",
      "subCat": "入門指南"
    },
    {
      "name": "範例",
      "file": "examples.md",
      "subCat": "入門指南"
    },
    {
      "name": "設定選項",
      "file": "configuration-options.md",
      "subCat": "設定"
    },
    {
      "name": "響應式設計",
      "file": "responsive-design.md",
      "subCat": "設定"
    },
    {
      "name": "自訂",
      "file": "customization.md",
      "subCat": "自訂"
    },
    {
      "name": "即時同步",
      "file": "live-sync.md",
      "subCat": "進階"
    },
    {
      "name": "API 參考",
      "file": "api-reference.md",
      "subCat": "進階"
    }
  ]
}